README.rst
setup.py
encviewfuse_decryptorui/__init__.py
encviewfuse_decryptorui.egg-info/PKG-INFO
encviewfuse_decryptorui.egg-info/SOURCES.txt
encviewfuse_decryptorui.egg-info/dependency_links.txt
encviewfuse_decryptorui.egg-info/entry_points.txt
encviewfuse_decryptorui.egg-info/requires.txt
encviewfuse_decryptorui.egg-info/top_level.txt
encviewfuse_decryptorui/decryptorui/DecryptionUI.py
encviewfuse_decryptorui/decryptorui/FilenameUtils.py
encviewfuse_decryptorui/decryptorui/SegmentedVirtualFile.py
encviewfuse_decryptorui/decryptorui/__init__.py