Metadata-Version: 1.1
Name: encviewfuse-decryptorui
Version: 0.4.0
Summary: A UI for decrypting directories and files encrypted with encviewfuse_decryptorui.
Home-page: https://github.com/seiferma/encviewfuse_decryptorui
Author: Stephan Seifermann
Author-email: seiferma@t-online.de
License: MIT
Keywords: decryption ui
Platform: UNKNOWN
Classifier: Development Status :: 5 - Production/Stable
Classifier: Environment :: Other Environment
Classifier: Intended Audience :: End Users/Desktop
Classifier: Topic :: Security :: Cryptography
Classifier: License :: OSI Approved :: MIT License
Classifier: Operating System :: OS Independent
Classifier: Programming Language :: Python :: 3 :: Only
